{
  "title": "2024>情報処理技術系>問題と解説>16 - 医療情報技師試験対策wiki",
  "question": "問16\n\nリレーショナルモデルの特徴はどれか。\n1)    データを木構造で表現する。\n2)    「タグ」と「エレメント」で内容を表現する。\n3)    データは他の多数のデータとつながり、網状の構造を持つ。\n4)    データはテーブルに格納され、テーブルの間は相互に関係を結ぶことができる。\n5)    データ値を格納するデータ部と各セル間の関係を示すポインタ部から構成されている。\n",
  "select1": "   データを木構造で表現する。",
  "select2": "   「タグ」と「エレメント」で内容を表現する。",
  "select3": "   データは他の多数のデータとつながり、網状の構造を持つ。",
  "select4": "   データはテーブルに格納され、テーブルの間は相互に関係を結ぶことができる。",
  "select5": "   データ値を格納するデータ部と各セル間の関係を示すポインタ部から構成されている。",
  "answer": "4",
  "url": "https://iryoujyouhou.wiki.fc2.com/wiki/2024>情報処理技術系>問題と解説>16"
}