{
  "title": "2019>医療情報システム系>問題と解説>51 - 医療情報技師試験対策wiki",
  "question": "問51\n電子カルテ端末の反応が遅くなった原因がネットワークに関連する事象であることを\n確認するのに適切なのはどれか。\n1)PCを予備機に交換する。\n2)ハードディスクの最適化を行う。\n3)ネットワークの経路を変更する。\n4)PCのメモリの使用量を確認する。\n5)電子カルテ以外のアプリケーションの動作を確認する。",
  "select1": "1)PCを予備機に交換する。",
  "select2": "2)ハードディスクの最適化を行う。",
  "select3": "3)ネットワークの経路を変更する。",
  "select4": "4)PCのメモリの使用量を確認する。",
  "select5": "5)電子カルテ以外のアプリケーションの動作を確認する。",
  "answer": "3,5",
  "url": "https://iryoujyouhou.wiki.fc2.com/wiki/2019>医療情報システム系>問題と解説>51"
}