{
  "title": "2019>医療情報システム系>問題と解説>23 - 医療情報技師試験対策wiki",
  "question": "問23\n医用画像表示用モニタ（医用モニタ）利用および管理について誤っているのはどれか。\n1)不変性試験と受け入れ試験の双方が必要である。\n2)医用モニタ品質管理責任者は導入、維持管理、対応について責任を行う。\n3)スクリーンセーバーを用いてもバックライトの寿命を延ばすことはできない。\n4)読影を行う場合は医療機器である医用モニタを使用する必要がある。\n5)医用モニタの品質管理に関する業務の一部は医療機関外部に委託することができる。",
  "select1": "1)不変性試験と受け入れ試験の双方が必要である。",
  "select2": "2)医用モニタ品質管理責任者は導入、維持管理、対応について責任を行う。",
  "select3": "3)スクリーンセーバーを用いてもバックライトの寿命を延ばすことはできない。",
  "select4": "4)読影を行う場合は医療機器である医用モニタを使用する必要がある。",
  "select5": "5)医用モニタの品質管理に関する業務の一部は医療機関外部に委託することができる。",
  "answer": "4",
  "url": "https://iryoujyouhou.wiki.fc2.com/wiki/2019>医療情報システム系>問題と解説>23"
}