{
  "title": "2024>医療情報システム系>問題と解説>53 - 医療情報技師試験対策wiki",
  "question": "問53\n\nSNOMED-CTの説明で適切なのはどれか。\n1)    疫学的研究を促進するための国際規格である。\n2)    臨床分野で利用される用語などを体系的に網羅している。\n3)    生涯に渡る診療情報について適切な共有方法を目指している。\n4)    健康状況と健康関連状況を記述するための概念的枠組みである。\n5)    臨床に関わるデータの一連の流れに関わる業務を標準化している。\n",
  "select1": "   疫学的研究を促進するための国際規格である。",
  "select2": "   臨床分野で利用される用語などを体系的に網羅している。",
  "select3": "   生涯に渡る診療情報について適切な共有方法を目指している。",
  "select4": "   健康状況と健康関連状況を記述するための概念的枠組みである。",
  "select5": "   臨床に関わるデータの一連の流れに関わる業務を標準化している。",
  "answer": "２",
  "url": "https://iryoujyouhou.wiki.fc2.com/wiki/2024>医療情報システム系>問題と解説>53"
}