{
  "title": "2012>情報処理技術系>問題と解説>08 - 医療情報技師試験対策wiki",
  "question": "問8\nRAID5の説明のうち正しいのはどれか。\n1)構成に必要な最低台数は4台である。\n2)同じ内容のデータを複数のハードディスクに書き込む。\n3)使用可能容量は構成台数から2台分をひいたものとなる。\n4)1台のハードディスクが故障してもデータの回復ができる。\n5)パリティの保存に使われるハードディスクが決まっている。",
  "select1": "1)構成に必要な最低台数は4台である。",
  "select2": "2)同じ内容のデータを複数のハードディスクに書き込む。",
  "select3": "3)使用可能容量は構成台数から2台分をひいたものとなる。",
  "select4": "4)1台のハードディスクが故障してもデータの回復ができる。",
  "select5": "5)パリティの保存に使われるハードディスクが決まっている。",
  "answer": "4",
  "url": "https://iryoujyouhou.wiki.fc2.com/wiki/2012>情報処理技術系>問題と解説>08"
}