{
  "title": "2015>医療情報システム系>問題と解説>16 - 医療情報技師試験対策wiki",
  "question": "問16\n入院処方オーダの運用に関して適切なのはどれか。2つマークしなさい。\n1)分量については1回量を入力することにした。\n2)1回の服用ごとに実施入力を行うようにした。\n3)誤入力を防ぐため投与量の入力単位をmgに統一した。\n4)オーダ発行、実施入力とも、一般名で入力するようにした。\n5)入力を簡便化するため最初の2文字だけで検索できるようにした。",
  "select1": "1)分量については1回量を入力することにした。",
  "select2": "2)1回の服用ごとに実施入力を行うようにした。",
  "select3": "3)誤入力を防ぐため投与量の入力単位をmgに統一した。",
  "select4": "4)オーダ発行、実施入力とも、一般名で入力するようにした。",
  "select5": "5)入力を簡便化するため最初の2文字だけで検索できるようにした。",
  "answer": "1,2",
  "url": "https://iryoujyouhou.wiki.fc2.com/wiki/2015>医療情報システム系>問題と解説>16"
}