{
  "title": "2019>医学医療系>問題と解説>09 - 医療情報技師試験対策wiki",
  "question": "問9\n医師法について正しいのはどれか。2つマークしなさい。\n\n1)診療録は10年間保存しなければならない。\n2)自ら検案をしないで検案書を交付することは禁止されている。\n3)医師は診療終了後7日目までに診療録を記載しなくてはならない。\n4)慢性疾患の患者については、診察を行わずに処方箋を発行できる。\n5)薬剤を調剤して投与する必要がある場合には、処方箋を交付しなければならない。\n",
  "select1": "1)診療録は10年間保存しなければならない。",
  "select2": "2)自ら検案をしないで検案書を交付することは禁止されている。",
  "select3": "3)医師は診療終了後7日目までに診療録を記載しなくてはならない。",
  "select4": "4)慢性疾患の患者については、診察を行わずに処方箋を発行できる。",
  "select5": "5)薬剤を調剤して投与する必要がある場合には、処方箋を交付しなければならない。",
  "answer": "2,5",
  "url": "https://iryoujyouhou.wiki.fc2.com/wiki/2019>医学医療系>問題と解説>09"
}