{
  "title": "2014>医療情報システム系>問題と解説>54 - 医療情報技師試験対策wiki",
  "question": "問54\n標準規格についての説明として誤っているのはどれか。2つマーク\n1) CDAはHL7で開発された規格である。\n2) IHEは業務ワークフローを定めた標準規格である。\n3) DICOMは医用画像交換のための標準規格である。\n4) JLAC10は画像検査項目を定めた標準規格である。\n5) HL7は検査情報などの情報交換のための標準規格である。",
  "select1": "CDAはHL7で開発された規格である。",
  "select2": "IHEは業務ワークフローを定めた標準規格である。",
  "select3": "DICOMは医用画像交換のための標準規格である。",
  "select4": "JLAC10は画像検査項目を定めた標準規格である。",
  "select5": "HL7は検査情報などの情報交換のための標準規格である。",
  "answer": "2,4",
  "url": "https://iryoujyouhou.wiki.fc2.com/wiki/2014>医療情報システム系>問題と解説>54"
}